pyfirefly/__init__.py
pyfirefly/exceptions.py
pyfirefly/models.py
pyfirefly/py.typed
pyfirefly/pyfirefly.py
pyfirefly-0.1.10.dist-info/METADATA
pyfirefly-0.1.10.dist-info/WHEEL
pyfirefly-0.1.10.dist-info/licenses/LICENSE
pyfirefly-0.1.10.dist-info/RECORD
