Metadata-Version: 2.4
Name: pyfirefly
Version: 0.1.10
Summary: Asynchronous Python client for the Firefly III API
Project-URL: Homepage, https://github.com/erwindouna/pyfirefly
Project-URL: Repository, https://github.com/erwindouna/pyfirefly
Project-URL: Documentation, https://github.com/erwindouna/pyfirefly
Project-URL: Bug Tracker, https://github.com/erwindouna/pyfirefly/issues
Project-URL: Changelog, https://github.com/erwindouna/pyfirefly/releases
Author-email: Erwin Douna <e.douna@gmail.com>
Maintainer-email: Erwin Douna <e.douna@gmail.com>
License-Expression: MIT
License-File: LICENSE
Keywords: api,async,client,python-firefly
Classifier: Framework :: AsyncIO
Classifier: Intended Audience :: Developers
Classifier: License :: OSI Approved :: MIT License
Classifier: Natural Language :: English
Classifier: Programming Language :: Python :: 3
Classifier: Programming Language :: Python :: 3.11
Classifier: Programming Language :: Python :: 3.12
Classifier: Programming Language :: Python :: 3.13
Classifier: Topic :: Software Development :: Libraries :: Python Modules
Requires-Python: <4,>=3.11
Requires-Dist: aiohttp>=3.0.0
Requires-Dist: mashumaro>=3.15
Requires-Dist: orjson<4,>=3.10.16
Requires-Dist: yarl>=1.6.0
